fico21softlibs/__init__.py
fico21softlibs/common.py
fico21softlibs/import_all.py
fico21softlibs/settings.py
fico21softlibs-0.9.83.dist-info/METADATA
fico21softlibs-0.9.83.dist-info/WHEEL
fico21softlibs-0.9.83.dist-info/top_level.txt
fico21softlibs-0.9.83.dist-info/RECORD
